[
 {
  "attached_to_doctype": null, 
  "attached_to_name": null, 
  "content_hash": null, 
  "docstatus": 0, 
  "doctype": "File", 
  "file_name": "Home", 
  "file_size": 179331, 
  "file_url": null, 
  "folder": null, 
  "is_attachments_folder": 0, 
  "is_folder": 1, 
  "is_home_folder": 1, 
  "is_private": 0, 
  "lft": 1, 
  "modified": "2018-03-24 14:11:02.400840", 
  "name": "Home", 
  "old_parent": "", 
  "rgt": 16, 
  "thumbnail_url": null
 }, 
 {
  "attached_to_doctype": null, 
  "attached_to_name": null, 
  "content_hash": null, 
  "docstatus": 0, 
  "doctype": "File", 
  "file_name": "Attachments", 
  "file_size": 179331, 
  "file_url": null, 
  "folder": "Home", 
  "is_attachments_folder": 1, 
  "is_folder": 1, 
  "is_home_folder": 0, 
  "is_private": 0, 
  "lft": 2, 
  "modified": "2018-03-24 14:11:02.400840", 
  "name": "Home/Attachments", 
  "old_parent": "Home", 
  "rgt": 15, 
  "thumbnail_url": null
 }, 
 {
  "attached_to_doctype": null, 
  "attached_to_name": null, 
  "content_hash": "79384364a804ed58fed5687ef343e131", 
  "docstatus": 0, 
  "doctype": "File", 
  "file_name": "l.png", 
  "file_size": 59678, 
  "file_url": "/private/files/l.png", 
  "folder": "Home/Attachments", 
  "is_attachments_folder": 0, 
  "is_folder": 0, 
  "is_home_folder": 0, 
  "is_private": 1, 
  "lft": 3, 
  "modified": "2017-02-19 09:07:59.490370", 
  "name": "5bb68b379e", 
  "old_parent": "Home/Attachments", 
  "rgt": 4, 
  "thumbnail_url": null
 }, 
 {
  "attached_to_doctype": null, 
  "attached_to_name": null, 
  "content_hash": "1427409b29bc62197800674002a40d5f", 
  "docstatus": 0, 
  "doctype": "File", 
  "file_name": "logo.png", 
  "file_size": 9073, 
  "file_url": "/private/files/logo.png", 
  "folder": "Home/Attachments", 
  "is_attachments_folder": 0, 
  "is_folder": 0, 
  "is_home_folder": 0, 
  "is_private": 1, 
  "lft": 5, 
  "modified": "2017-02-19 09:08:31.223912", 
  "name": "b0629eded3", 
  "old_parent": "Home/Attachments", 
  "rgt": 6, 
  "thumbnail_url": null
 }, 
 {
  "attached_to_doctype": null, 
  "attached_to_name": null, 
  "content_hash": "db6fce6ba1f50adc1c73d274ece3827f", 
  "docstatus": 0, 
  "doctype": "File", 
  "file_name": "image001.png", 
  "file_size": 7379, 
  "file_url": "/private/files/image001.png", 
  "folder": "Home/Attachments", 
  "is_attachments_folder": 0, 
  "is_folder": 0, 
  "is_home_folder": 0, 
  "is_private": 1, 
  "lft": 7, 
  "modified": "2017-02-19 09:09:59.900960", 
  "name": "758caa37c6", 
  "old_parent": "Home/Attachments", 
  "rgt": 8, 
  "thumbnail_url": null
 }, 
 {
  "attached_to_doctype": "User", 
  "attached_to_name": "mantas.kalinauskas@bekredito.lt", 
  "content_hash": "572f2bdb5777ea332c34f34c86198613", 
  "docstatus": 0, 
  "doctype": "File", 
  "file_name": "Build-Bigger-Biceps-With-Isometrics-new.png", 
  "file_size": 54269, 
  "file_url": "/files/Build-Bigger-Biceps-With-Isometrics-new.png", 
  "folder": "Home/Attachments", 
  "is_attachments_folder": 0, 
  "is_folder": 0, 
  "is_home_folder": 0, 
  "is_private": 0, 
  "lft": 9, 
  "modified": "2017-06-29 11:03:40.385055", 
  "name": "39f8233089", 
  "old_parent": "Home/Attachments", 
  "rgt": 10, 
  "thumbnail_url": null
 }, 
 {
  "attached_to_doctype": null, 
  "attached_to_name": null, 
  "content_hash": "4923aacb337b2c23556e030c3b5b8434", 
  "docstatus": 0, 
  "doctype": "File", 
  "file_name": "logo5b8434.png", 
  "file_size": 24466, 
  "file_url": "/private/files/logo5b8434.png", 
  "folder": "Home/Attachments", 
  "is_attachments_folder": 0, 
  "is_folder": 0, 
  "is_home_folder": 0, 
  "is_private": 1, 
  "lft": 11, 
  "modified": "2018-03-24 13:41:01.559540", 
  "name": "25b06f2c4f", 
  "old_parent": "Home/Attachments", 
  "rgt": 12, 
  "thumbnail_url": null
 }, 
 {
  "attached_to_doctype": null, 
  "attached_to_name": null, 
  "content_hash": "4923aacb337b2c23556e030c3b5b8434", 
  "docstatus": 0, 
  "doctype": "File", 
  "file_name": "logo5b8434.png", 
  "file_size": 24466, 
  "file_url": "/private/files/logo5b8434.png", 
  "folder": "Home/Attachments", 
  "is_attachments_folder": 0, 
  "is_folder": 0, 
  "is_home_folder": 0, 
  "is_private": 1, 
  "lft": 13, 
  "modified": "2018-03-24 14:11:02.443702", 
  "name": "c54ea9f472", 
  "old_parent": "Home/Attachments", 
  "rgt": 14, 
  "thumbnail_url": null
 }
]